macpie/__init__.py
macpie/_compat.py
macpie/_config/__init__.py
macpie/_config/config.py
macpie/cli/__init__.py
macpie/cli/core.py
macpie/cli/env.py
macpie/cli/helpers.py
macpie/cli/macpie/__init__.py
macpie/cli/macpie/envfile.py
macpie/cli/macpie/keepone.py
macpie/cli/macpie/link.py
macpie/cli/macpie/main.py
macpie/cli/macpie/masker.py
macpie/cli/macpie/merge.py
macpie/cli/macpie/replace.py
macpie/cli/mppair/__init__.py
macpie/cli/mppair/compare.py
macpie/cli/mppair/conform.py
macpie/cli/mppair/helpers.py
macpie/cli/mppair/main.py
macpie/cli/mppair/replace.py
macpie/cli/mppair/subset.py
macpie/cli/mpsql/__init__.py
macpie/cli/mpsql/createproc.py
macpie/cli/mpsql/createtable.py
macpie/cli/mpsql/dbconnections.py
macpie/cli/mpsql/helpers.py
macpie/cli/mpsql/main.py
macpie/cli/mpsql/masktable.py
macpie/core/__init__.py
macpie/core/api.py
macpie/core/combine.py
macpie/core/common.py
macpie/core/config_init.py
macpie/core/dataset.py
macpie/core/datasetfields.py
macpie/core/exceptions.py
macpie/core/groupby.py
macpie/core/macseries.py
macpie/core/collections/__init__.py
macpie/core/collections/anchoredlist.py
macpie/core/collections/base.py
macpie/core/collections/basiclist.py
macpie/core/collections/mergeableanchoredlist.py
macpie/core/collections/graph/__init__.py
macpie/core/collections/graph/basicgraph.py
macpie/core/collections/graph/executablegraph.py
macpie/io/__init__.py
macpie/io/api.py
macpie/io/utils.py
macpie/io/excel/__init__.py
macpie/io/excel/_base.py
macpie/io/excel/_openpyxl.py
macpie/io/excel/_xlsxwriter.py
macpie/io/formats/__init__.py
macpie/io/formats/excel.py
macpie/io/formats/style.py
macpie/io/json/__init__.py
macpie/io/json/_json.py
macpie/io/json/_table_schema.py
macpie/pandas/__init__.py
macpie/pandas/combine.py
macpie/pandas/compare.py
macpie/pandas/convert.py
macpie/pandas/describe.py
macpie/pandas/groupby.py
macpie/pandas/indexing.py
macpie/pandas/io.py
macpie/pandas/select.py
macpie/pandas/sort.py
macpie/pandas/accessors/__init__.py
macpie-0.7.0.dist-info/LICENSE.rst
macpie-0.7.0.dist-info/METADATA
macpie-0.7.0.dist-info/WHEEL
macpie-0.7.0.dist-info/entry_points.txt
macpie-0.7.0.dist-info/top_level.txt
macpie-0.7.0.dist-info/RECORD
