Metadata-Version: 2.1
Name: macpie
Version: 0.7.0
Summary: A Python library and command line tool for clinical research data analysis.
Home-page: https://github.com/UCSFMemoryAndAging/macpie
Maintainer: Regents of the University of California
Maintainer-email: albert.lee2@ucsf.edu
License: BSD-2-Clause
Project-URL: Code, https://github.com/UCSFMemoryAndAging/macpie
Classifier: Development Status :: 4 - Beta
Classifier: Intended Audience :: Developers
Classifier: Intended Audience :: Education
Classifier: Intended Audience :: End Users/Desktop
Classifier: Intended Audience :: Science/Research
Classifier: License :: OSI Approved :: BSD License
Classifier: Operating System :: OS Independent
Classifier: Programming Language :: Python :: 3
Classifier: Topic :: Scientific/Engineering :: Information Analysis
Classifier: Topic :: Software Development :: Libraries :: Python Modules
Requires-Python: >=3.9
License-File: LICENSE.rst
Requires-Dist: pandas (<2.0.0,>=1.3)
Requires-Dist: click (>=8.0)
Requires-Dist: openpyxl (>=3.0)
Requires-Dist: XlsxWriter (>=3.0)
Requires-Dist: python-dotenv (>=0.20)
Requires-Dist: tablib (>=3.0)
Requires-Dist: tabulate (>=0.8)
Requires-Dist: packaging
Provides-Extra: all
Requires-Dist: mysql-connector-python (>=8.0) ; extra == 'all'
Requires-Dist: SQLAlchemy (>=1.3) ; extra == 'all'
Requires-Dist: matplotlib (>=3.5) ; extra == 'all'
Requires-Dist: networkx (>=2.8) ; extra == 'all'
Provides-Extra: all_cli
Requires-Dist: mysql-connector-python (>=8.0) ; extra == 'all_cli'
Requires-Dist: SQLAlchemy (>=1.3) ; extra == 'all_cli'
Provides-Extra: mpsql
Requires-Dist: mysql-connector-python (>=8.0) ; extra == 'mpsql'
Requires-Dist: SQLAlchemy (>=1.3) ; extra == 'mpsql'
